basilisk/__init__.py
basilisk/__main__.py
basilisk/build_wasm_binary_or_exit.py
basilisk/cargotoml.py
basilisk/colors.py
basilisk/module_bundler.py
basilisk/py.typed
basilisk/run_basilisk_generate_or_exit.py
basilisk/timed.py
basilisk/types.py
basilisk/canisters/__init__.py
basilisk/canisters/ledger/NOTICE
basilisk/canisters/ledger/__init__.py
basilisk/canisters/management/__init__.py
basilisk/canisters/management/basic.py
basilisk/canisters/management/bitcoin.py
basilisk/canisters/management/http.py
basilisk/canisters/management/tecdsa.py
basilisk/compiler/LICENSE-RustPython
basilisk/compiler/__init__.py
basilisk/compiler/install_rust_dependencies.sh
basilisk/compiler/python_3_10_13_licenses.pdf
basilisk/compiler/__pycache__/__init__.cpython-310.pyc
basilisk/compiler/basilisk_compile_python_stdlib/Cargo.toml
basilisk/compiler/basilisk_compile_python_stdlib/src/main.rs
basilisk/compiler/basilisk_generate/Cargo.toml
basilisk/compiler/basilisk_generate/src/constants.rs
basilisk/compiler/basilisk_generate/src/exit_codes.rs
basilisk/compiler/basilisk_generate/src/get_child_class_of.rs
basilisk/compiler/basilisk_generate/src/get_name.rs
basilisk/compiler/basilisk_generate/src/get_subscript_slice.rs
basilisk/compiler/basilisk_generate/src/keywords.rs
basilisk/compiler/basilisk_generate/src/lib.rs
basilisk/compiler/basilisk_generate/src/main.rs
basilisk/compiler/basilisk_generate/src/tuple.rs
basilisk/compiler/basilisk_generate/src/body/async_result_handler.rs
basilisk/compiler/basilisk_generate/src/body/call_global_python_function.rs
basilisk/compiler/basilisk_generate/src/body/guard_against_non_controllers.rs
basilisk/compiler/basilisk_generate/src/body/mod.rs
basilisk/compiler/basilisk_generate/src/body/unwrap_rust_python_result.rs
basilisk/compiler/basilisk_generate/src/body/utils.rs
basilisk/compiler/basilisk_generate/src/candid_type/array.rs
basilisk/compiler/basilisk_generate/src/candid_type/mod.rs
basilisk/compiler/basilisk_generate/src/candid_type/opt.rs
ic_basilisk-0.7.2.dist-info/licenses/LICENSE
ic_basilisk-0.7.2.dist-info/licenses/NOTICE
ic_basilisk-0.7.2.dist-info/licenses/NOTICE_PYTHON
ic_basilisk-0.7.2.dist-info/METADATA
ic_basilisk-0.7.2.dist-info/WHEEL
ic_basilisk-0.7.2.dist-info/top_level.txt
ic_basilisk-0.7.2.dist-info/RECORD
